<?xml version="1.0" encoding="utf-8" ?>
<dwsync>
<file name="aii.svg" server="www.directalloys.com/www.cmmportfolio.com/" local="131628861784104095" remote="131890450200000000" Dst="1" />
<file name="blackFace.svg" server="www.directalloys.com/www.cmmportfolio.com/" local="131628851540457969" remote="131890450200000000" Dst="1" />
<file name="dodec.svg" server="www.directalloys.com/www.cmmportfolio.com/" local="131565425906928397" remote="131890450200000000" Dst="1" />
<file name="faces.svg" server="www.directalloys.com/www.cmmportfolio.com/" local="131628759493885840" remote="131890450200000000" Dst="1" />
<file name="mf logo.jpg" server="www.directalloys.com/www.cmmportfolio.com/" local="131787252422370575" remote="131890450200000000" Dst="1" />
<file name="pacha1.svg" server="www.directalloys.com/www.cmmportfolio.com/" local="131422278120000000" remote="131890450200000000" Dst="1" />
<file name="sacral.svg" server="www.directalloys.com/www.cmmportfolio.com/" local="131628843247827636" remote="131890450200000000" Dst="1" />
<file name="sahasrara.jpg" server="www.directalloys.com/www.cmmportfolio.com/" local="131565427718349155" remote="131890450200000000" Dst="1" />
</dwsync>